{
"type": "FeatureCollection",
"crs": { "type": "name", "properties": { "name": "urn:ogc:def:crs:OGC:1.3:CRS84" } },
"features": [
{ "type": "Feature", "properties": { "Clustermasses": 823.09253084395959, "Type": "Lihakarjan lietelanta eläinsuojasta", "lon": 23.392962309133782, "lat": 60.950312391942617 }, "geometry": { "type": "Point", "coordinates": [ 23.392962309133782, 60.950312391942617 ] } },
{ "type": "Feature", "properties": { "Clustermasses": 869.6031891587711, "Type": "Lihakarjan lietelanta eläinsuojasta", "lon": 23.396818468407783, "lat": 60.90530520090158 }, "geometry": { "type": "Point", "coordinates": [ 23.396818468407783, 60.90530520090158 ] } },
{ "type": "Feature", "properties": { "Clustermasses": 837.29618133165718, "Type": "Lihakarjan lietelanta eläinsuojasta", "lon": 23.311923830026185, "lat": 60.938378560827601 }, "geometry": { "type": "Point", "coordinates": [ 23.311923830026185, 60.938378560827601 ] } },
{ "type": "Feature", "properties": { "Clustermasses": 640.90425592225279, "Type": "Lihakarjan lietelanta eläinsuojasta", "lon": 23.30790699452912, "lat": 60.896464967782137 }, "geometry": { "type": "Point", "coordinates": [ 23.30790699452912, 60.896464967782137 ] } },
{ "type": "Feature", "properties": { "Clustermasses": 5996.6482688803844, "Type": "Lihakarjan lietelanta eläinsuojasta", "lon": 23.489159577636382, "lat": 60.956084864825833 }, "geometry": { "type": "Point", "coordinates": [ 23.489159577636382, 60.956084864825833 ] } },
{ "type": "Feature", "properties": { "Clustermasses": 1088.8208734683835, "Type": "Lihakarjan lietelanta eläinsuojasta", "lon": 23.504694377373369, "lat": 60.926766513185527 }, "geometry": { "type": "Point", "coordinates": [ 23.504694377373369, 60.926766513185527 ] } },
{ "type": "Feature", "properties": { "Clustermasses": 1270.2459831353622, "Type": "Lihakarjan lietelanta eläinsuojasta", "lon": 23.494748003405846, "lat": 60.902490275292429 }, "geometry": { "type": "Point", "coordinates": [ 23.494748003405846, 60.902490275292429 ] } },
{ "type": "Feature", "properties": { "Clustermasses": 711.19191699245823, "Type": "Lihakarjan lietelanta eläinsuojasta", "lon": 23.391904956530695, "lat": 60.995867445404969 }, "geometry": { "type": "Point", "coordinates": [ 23.391904956530695, 60.995867445404969 ] } },
{ "type": "Feature", "properties": { "Clustermasses": 1130.7140081909279, "Type": "Lihakarjan lietelanta eläinsuojasta", "lon": 23.368261159985789, "lat": 60.861814441630273 }, "geometry": { "type": "Point", "coordinates": [ 23.368261159985789, 60.861814441630273 ] } },
{ "type": "Feature", "properties": { "Clustermasses": 572.58610841318909, "Type": "Lihakarjan lietelanta eläinsuojasta", "lon": 23.325676175569132, "lat": 60.995067155343627 }, "geometry": { "type": "Point", "coordinates": [ 23.325676175569132, 60.995067155343627 ] } },
{ "type": "Feature", "properties": { "Clustermasses": 708.53830842044431, "Type": "Lihakarjan lietelanta eläinsuojasta", "lon": 23.270311726570682, "lat": 60.979524654338441 }, "geometry": { "type": "Point", "coordinates": [ 23.270311726570682, 60.979524654338441 ] } }
]
}
