{
"type": "FeatureCollection",
"crs": { "type": "name", "properties": { "name": "urn:ogc:def:crs:OGC:1.3:CRS84" } },
"features": [
{ "type": "Feature", "properties": { "Clustermasses": 2909.1468023578045, "Type": "Emakot ja porsaat lietelanta eläinsuojasta", "lon": 23.399350137436858, "lat": 60.914960504456261 }, "geometry": { "type": "Point", "coordinates": [ 23.399350137436858, 60.914960504456261 ] } },
{ "type": "Feature", "properties": { "Clustermasses": 2524.9178680138111, "Type": "Emakot ja porsaat lietelanta eläinsuojasta", "lon": 23.355859586129114, "lat": 60.952313373293073 }, "geometry": { "type": "Point", "coordinates": [ 23.355859586129114, 60.952313373293073 ] } }
]
}
